cfnjsontoyaml/__init__.py
cfnjsontoyaml/__main__.py
cfnjsontoyaml/convertor.py
cfnjsontoyaml/functionparser.py
cfnjsontoyaml/nodeparser.py
cfnjsontoyaml/mixins/__init__.py
cfnjsontoyaml/mixins/type_checker.py
cfnjsontoyaml/parser/__init__.py
cfnjsontoyaml/parser/subbuilder.py
cfnjsontoyaml/yamlobject/__init__.py
cfnjsontoyaml/yamlobject/base64.py
cfnjsontoyaml/yamlobject/cfnfunction.py
cfnjsontoyaml/yamlobject/equals.py
cfnjsontoyaml/yamlobject/findinmap.py
cfnjsontoyaml/yamlobject/fnand.py
cfnjsontoyaml/yamlobject/fnif.py
cfnjsontoyaml/yamlobject/fnnot.py
cfnjsontoyaml/yamlobject/fnor.py
cfnjsontoyaml/yamlobject/getatt.py
cfnjsontoyaml/yamlobject/getazs.py
cfnjsontoyaml/yamlobject/importvalue.py
cfnjsontoyaml/yamlobject/join.py
cfnjsontoyaml/yamlobject/ordereddict.py
cfnjsontoyaml/yamlobject/ref.py
cfnjsontoyaml/yamlobject/select.py
cfnjsontoyaml/yamlobject/sub.py
cfnjsontoyaml/yamlobject/unicode.py
cfnjsontoyaml-1.0.5.dist-info/DESCRIPTION.rst
cfnjsontoyaml-1.0.5.dist-info/METADATA
cfnjsontoyaml-1.0.5.dist-info/RECORD
cfnjsontoyaml-1.0.5.dist-info/WHEEL
cfnjsontoyaml-1.0.5.dist-info/entry_points.txt
cfnjsontoyaml-1.0.5.dist-info/metadata.json
cfnjsontoyaml-1.0.5.dist-info/top_level.txt
