Metadata-Version: 2.0
Name: cfnjsontoyaml
Version: 1.0.5
Summary: UNKNOWN
Home-page: https://github.com/drewsonne/cfn-json-to-yaml
Author: Drew J. Sonne
Author-email: drew.sonne@gmail.com
License: LGPL
Download-URL: https://github.com/drewsonne/cfn-json-to-yaml/archive/v.1.0.5.zip
Platform: UNKNOWN
Requires-Dist: pyyaml
Requires-Dist: six
